eesyldap/__init__.py
eesyldap/attributes.py
eesyldap/client.py
eesyldap/connection.py
eesyldap/entry.py
eesyldap/exceptions.py
eesyldap/filters.py
eesyldap/helpers.py
eesyldap/object.py
eesyldap/relations.py
eesyldap/search.py
eesyldap/unicity.py
eesyldap-0.3.0.dist-info/WHEEL
eesyldap-0.3.0.dist-info/METADATA
eesyldap-0.3.0.dist-info/RECORD
