Metadata-Version: 2.1
Name: eesyldap
Version: 0.3.0
Summary: Simple LDAP Objects mapper
Home-page: https://gitlab.easter-eggs.com/brenard/eesyldap
Author: Benjamin Renard
Author-email: brenard@easter-eggs.com
Requires-Python: >=3.7,<4.0
Classifier: Programming Language :: Python
Classifier: Programming Language :: Python :: 3
Classifier: Programming Language :: Python :: 3.7
Classifier: Programming Language :: Python :: 3.8
Classifier: Topic :: Software Development :: Libraries :: Python Modules
Requires-Dist: beaker (>=1.11.0,<2.0.0)
Requires-Dist: passlib (>=1.7.2,<2.0.0)
Requires-Dist: python-dateutil (>=2.8.1,<3.0.0)
Requires-Dist: python-ldap
Requires-Dist: pytz (>=2019.3,<2020.0)
Requires-Dist: unidecode (>=1.1.1,<2.0.0)
Project-URL: Repository, https://gitlab.easter-eggs.com/brenard/eesyldap
